{"imagePath":"矢量智能对象1_ske_tex.png","width":512,"SubTexture":[{"width":246,"y":545,"height":40,"name":"shadow","x":1},{"width":69,"y":102,"height":103,"name":"图层_3","x":316},{"width":54,"y":207,"height":87,"name":"图层_5","x":316},{"width":289,"y":299,"height":244,"name":"C__0001_图层-0_1","x":1},{"width":103,"y":1,"height":99,"name":"图层_4","x":316},{"width":125,"y":299,"height":191,"name":"图层_2","x":292},{"width":313,"y":1,"height":296,"name":"图层_6","x":1},{"width":66,"y":207,"height":67,"name":"C__0000_图层-1","x":372}],"height":1024,"name":"矢量智能对象1_ske"}